joker_pyoneliner-0.1-py3.7-nspkg.pth
joker/pyoneliner/__init__.py
joker/pyoneliner/__main__.py
joker/pyoneliner/main.py
joker_pyoneliner-0.1.dist-info/METADATA
joker_pyoneliner-0.1.dist-info/WHEEL
joker_pyoneliner-0.1.dist-info/entry_points.txt
joker_pyoneliner-0.1.dist-info/namespace_packages.txt
joker_pyoneliner-0.1.dist-info/top_level.txt
joker_pyoneliner-0.1.dist-info/RECORD
